mylibrary/__init__.py
mylibrary/modul_lain.py
mylibrarylukheman-0.1.dist-info/METADATA
mylibrarylukheman-0.1.dist-info/WHEEL
mylibrarylukheman-0.1.dist-info/top_level.txt
mylibrarylukheman-0.1.dist-info/RECORD
