Metadata-Version: 2.1
Name: mylibrarylukheman
Version: 0.1
Summary: Library sederhana untuk menyapa orang
Home-page: https://github.com/lukheman/mylibrary
Author: Lukheman
Author-email: akmal@gmail.com
Requires-Python: >=3.6
